{
    "Xhaka_Arsenal": 3,
    "Elneny_Arsenal": 4,
    "Holding_Arsenal": 5,
    "Partey_Arsenal": 6,
    "\u00d8degaard_Arsenal": 7,
    "Tierney_Arsenal": 8,
    "P\u00e9p\u00e9_Arsenal": 9,
    "White_Arsenal": 10,
    "Nketiah_Arsenal": 11,
    "Smith Rowe_Arsenal": 12,
    "Saka_Arsenal": 13,
    "Tomiyasu_Arsenal": 14,
    "Ramsdale_Arsenal": 15,
    "Gabriel_Arsenal": 16,
    "Tavares_Arsenal": 17,
    "Martinelli_Arsenal": 19,
    "Pablo Mar\u00ed_Arsenal": 20,
    "Torreira_Arsenal": 22,
    "Nelson_Arsenal": 23,
    "Turner_Arsenal": 24,
    "F\u00e1bio Vieira_Arsenal": 25,
    "Saliba_Arsenal": 26,
    "Marquinhos_Arsenal": 27,
    "Jesus_Arsenal": 28,
    "Trossard_Arsenal": 111,
    "Jorginho_Arsenal": 130,
    "Zinchenko_Arsenal": 313,
    "Smith_Arsenal": 607,
    "Nwaneri_Arsenal": 630,
    "Sousa_Arsenal": 631,
    "Hein_Arsenal": 655,
    "Cozier-Duberry_Arsenal": 668,
    "Butler-Oyedeji_Arsenal": 685,
    "Kiwior_Arsenal": 710,
    "Walters_Arsenal": 751,
    "Coutinho_Aston Villa": 29,
    "Mart\u00ednez_Aston Villa": 31,
    "Chambers_Aston Villa": 32,
    "Digne_Aston Villa": 33,
    "Traor\u00e9_Aston Villa": 34,
    "Olsen_Aston Villa": 35,
    "Sanson_Aston Villa": 36,
    "McGinn_Aston Villa": 37,
    "Hause_Aston Villa": 38,
    "Mings_Aston Villa": 39,
    "Watkins_Aston Villa": 40,
    "Nakamba_Aston Villa": 41,
    "Buend\u00eda_Aston Villa": 42,
    "Cash_Aston Villa": 43,
    "Konsa_Aston Villa": 44,
    "Bailey_Aston Villa": 45,
    "Douglas Luiz_Aston Villa": 46,
    "Ramsey_Aston Villa": 47,
    "Iroegbunam_Aston Villa": 49,
    "Diego Carlos_Aston Villa": 50,
    "El Ghazi_Aston Villa": 51,
    "Davis_Aston Villa": 52,
    "Kamara_Aston Villa": 53,
    "Archer_Aston Villa": 54,
    "Philogene-Bidace_Aston Villa": 55,
    "Guilbert_Aston Villa": 56,
    "Dendoncker_Aston Villa": 479,
    "Augustinsson_Aston Villa": 525,
    "Kesler Hayden_Aston Villa": 537,
    "Young_Aston Villa": 538,
    "Bogarde_Aston Villa": 638,
    "Marschall_Aston Villa": 670,
    "Kadan Young_Aston Villa": 672,
    "\u00c1lex Moreno_Aston Villa": 694,
    "Sinisalo_Aston Villa": 707,
    "Dur\u00e1n_Aston Villa": 711,
    "Swinkels_Aston Villa": 744,
    "Zych_Aston Villa": 745,
    "Wright_Aston Villa": 753,
    "Revan_Aston Villa": 754,
    "Patterson_Aston Villa": 755,
    "O'Reilly_Aston Villa": 761,
    "Smith_Bournemouth": 57,
    "Stanislas_Bournemouth": 58,
    "Fredericks_Bournemouth": 59,
    "Brooks_Bournemouth": 60,
    "Lowe_Bournemouth": 61,
    "Moore_Bournemouth": 62,
    "Marcondes_Bournemouth": 63,
    "Lerma_Bournemouth": 64,
    "Stacey_Bournemouth": 65,
    "Solanke_Bournemouth": 66,
    "Cook_Bournemouth": 67,
    "Pearson_Bournemouth": 68,
    "Christie_Bournemouth": 69,
    "Billing_Bournemouth": 70,
    "Mepham_Bournemouth": 71,
    "Travers_Bournemouth": 72,
    "Kelly_Bournemouth": 73,
    "Demb\u00e9l\u00e9_Bournemouth": 74,
    "Anthony_Bournemouth": 75,
    "Zemura_Bournemouth": 76,
    "Dennis_Bournemouth": 77,
    "Stephens_Bournemouth": 404,
    "Rothwell_Bournemouth": 505,
    "Tavernier_Bournemouth": 535,
    "Hill_Bournemouth": 539,
    "Randolph_Bournemouth": 571,
    "Neto_Bournemouth": 574,
    "Senesi_Bournemouth": 576,
    "Saydee_Bournemouth": 597,
    "Bevan_Bournemouth": 598,
    "Plain_Bournemouth": 649,
    "Adu-Adjei_Bournemouth": 695,
    "Dacosta Gonzalez_Bournemouth": 696,
    "Sadi_Bournemouth": 697,
    "Ouattara_Bournemouth": 705,
    "Pollock_Bournemouth": 706,
    "Semenyo_Bournemouth": 714,
    "Vi\u00f1a_Bournemouth": 718,
    "Zabarnyi_Bournemouth": 722,
    "H.Traor\u00e8_Bournemouth": 723,
    "Greenwood_Bournemouth": 737,
    "Kinsey-Wellings_Bournemouth": 738,
    "Jansson_Brentford": 78,
    "N\u00f8rgaard_Brentford": 79,
    "Toney_Brentford": 80,
    "Raya_Brentford": 81,
    "Can\u00f3s_Brentford": 82,
    "Dasilva_Brentford": 83,
    "Ajer_Brentford": 84,
    "Henry_Brentford": 85,
    "Janelt_Brentford": 86,
    "Ghoddos_Brentford": 87,
    "Jensen_Brentford": 88,
    "Wissa_Brentford": 89,
    "Roerslev_Brentford": 90,
    "Bech_Brentford": 91,
    "Pinnock_Brentford": 92,
    "Onyeka_Brentford": 93,
    "Baptiste_Brentford": 94,
    "Mbeumo_Brentford": 95,
    "Goode_Brentford": 96,
    "Forss_Brentford": 97,
    "Thompson_Brentford": 98,
    "Bidstrup_Brentford": 99,
    "Balcombe_Brentford": 100,
    "Hickey_Brentford": 510,
    "Lewis-Potter_Brentford": 515,
    "Strakosha_Brentford": 517,
    "Mee_Brentford": 526,
    "Stevens_Brentford": 540,
    "Dervi\u015fo\u011flu_Brentford": 541,
    "Damsgaard_Brentford": 580,
    "Zanka_Brentford": 595,
    "Trevitt_Brentford": 632,
    "Cox_Brentford": 633,
    "Crama_Brentford": 646,
    "Yarmolyuk_Brentford": 650,
    "Schade_Brentford": 688,
    "Olakigbe_Brentford": 752,
    "Lallana_Brighton": 101,
    "Steele_Brighton": 102,
    "Welbeck_Brighton": 103,
    "Gro\u00df_Brighton": 104,
    "Dunk_Brighton": 106,
    "March_Brighton": 107,
    "Webster_Brighton": 108,
    "Veltman_Brighton": 109,
    "S\u00e1nchez_Brighton": 113,
    "Lamptey_Brighton": 114,
    "Alzate_Brighton": 115,
    "Mac Allister_Brighton": 116,
    "Moder_Brighton": 117,
    "Mwepu_Brighton": 118,
    "Sarmiento_Brighton": 119,
    "Caicedo_Brighton": 120,
    "Richards_Brighton": 121,
    "Roberts_Brighton": 122,
    "Undav_Brighton": 123,
    "Mitoma_Brighton": 124,
    "Enciso_Brighton": 125,
    "Koz\u0142owski_Brighton": 126,
    "Gilmour_Brighton": 149,
    "Scherpen_Brighton": 542,
    "Clarke_Brighton": 543,
    "Van Hecke_Brighton": 544,
    "Colwill_Brighton": 559,
    "Estupi\u00f1\u00e1n_Brighton": 586,
    "Ferguson_Brighton": 596,
    "Turns_Brighton": 640,
    "Moran_Brighton": 651,
    "Furlong_Brighton": 652,
    "Hinshelwood_Brighton": 677,
    "Buonanotte_Brighton": 679,
    "Ayari_Brighton": 719,
    "Offiah_Brighton": 736,
    "McGill_Brighton": 756,
    "Peupion_Brighton": 762,
    "Chukwuemeka_Chelsea": 48,
    "Cucurella_Chelsea": 112,
    "Azpilicueta_Chelsea": 127,
    "Thiago Silva_Chelsea": 128,
    "Alonso_Chelsea": 129,
    "Barkley_Chelsea": 131,
    "Kovacic_Chelsea": 132,
    "Arrizabalaga_Chelsea": 133,
    "Kant\u00e9_Chelsea": 134,
    "Ziyech_Chelsea": 135,
    "Loftus-Cheek_Chelsea": 136,
    "Werner_Chelsea": 137,
    "Kenedy_Chelsea": 138,
    "Chilwell_Chelsea": 139,
    "Pulisic_Chelsea": 140,
    "Chalobah_Chelsea": 141,
    "Mount_Chelsea": 142,
    "Sarr_Chelsea": 143,
    "Hudson-Odoi_Chelsea": 144,
    "Havertz_Chelsea": 145,
    "James_Chelsea": 146,
    "Mendy_Chelsea": 147,
    "Gallagher_Chelsea": 148,
    "Broja_Chelsea": 150,
    "Ampadu_Chelsea": 151,
    "W.Fofana_Chelsea": 272,
    "Sterling_Chelsea": 304,
    "Koulibaly_Chelsea": 520,
    "Vale_Chelsea": 606,
    "Zakaria_Chelsea": 616,
    "Aubameyang_Chelsea": 617,
    "Bettinelli_Chelsea": 635,
    "Hutchinson_Chelsea": 653,
    "Hall_Chelsea": 661,
    "Humphreys_Chelsea": 673,
    "D.D.Fofana_Chelsea": 684,
    "Badiashile_Chelsea": 689,
    "Jo\u00e3o F\u00e9lix_Chelsea": 690,
    "Mudryk_Chelsea": 699,
    "Andrey Santos_Chelsea": 702,
    "Madueke_Chelsea": 708,
    "Enzo_Chelsea": 724,
    "Sambi_Crystal Palace": 18,
    "Guaita_Crystal Palace": 152,
    "Tomkins_Crystal Palace": 153,
    "McArthur_Crystal Palace": 154,
    "Benteke_Crystal Palace": 155,
    "Ward_Crystal Palace": 156,
    "Clyne_Crystal Palace": 157,
    "Milivojevic_Crystal Palace": 158,
    "J.Ayew_Crystal Palace": 159,
    "Zaha_Crystal Palace": 160,
    "Schlupp_Crystal Palace": 161,
    "Hughes_Crystal Palace": 163,
    "Riedewald_Crystal Palace": 164,
    "Andersen_Crystal Palace": 165,
    "Edouard_Crystal Palace": 166,
    "Gu\u00e9hi_Crystal Palace": 167,
    "Mateta_Crystal Palace": 168,
    "Eze_Crystal Palace": 169,
    "Mitchell_Crystal Palace": 170,
    "Olise_Crystal Palace": 171,
    "Rak-Sakyi_Crystal Palace": 172,
    "Ebiowei_Crystal Palace": 173,
    "Ferguson_Crystal Palace": 174,
    "Johnstone_Crystal Palace": 175,
    "Matthews_Crystal Palace": 495,
    "Plange_Crystal Palace": 496,
    "C.Doucour\u00e9_Crystal Palace": 514,
    "Richards_Crystal Palace": 530,
    "Whitworth_Crystal Palace": 590,
    "Rodney_Crystal Palace": 601,
    "Phillips_Crystal Palace": 604,
    "Gordon_Crystal Palace": 634,
    "Balmer_Crystal Palace": 642,
    "Goodman_Crystal Palace": 644,
    "Wells-Morrison_Crystal Palace": 654,
    "Ozoh_Crystal Palace": 676,
    "Ahamada_Crystal Palace": 725,
    "Maupay_Everton": 110,
    "Begovi\u0107_Everton": 176,
    "Rond\u00f3n_Everton": 177,
    "Coleman_Everton": 178,
    "Townsend_Everton": 179,
    "Keane_Everton": 180,
    "Dele_Everton": 181,
    "Pickford_Everton": 182,
    "Allan_Everton": 183,
    "Andr\u00e9 Gomes_Everton": 184,
    "A.Doucour\u00e9_Everton": 185,
    "Iwobi_Everton": 186,
    "Gbamin_Everton": 187,
    "Mina_Everton": 188,
    "Gray_Everton": 189,
    "Davies_Everton": 190,
    "Calvert-Lewin_Everton": 191,
    "Holgate_Everton": 192,
    "Godfrey_Everton": 193,
    "Mykolenko_Everton": 194,
    "Branthwaite_Everton": 196,
    "Patterson_Everton": 197,
    "Nkounkou_Everton": 198,
    "Tarkowski_Everton": 199,
    "Coady_Everton": 475,
    "Vinagre_Everton": 531,
    "McNeil_Everton": 534,
    "Mills_Everton": 560,
    "Warrington_Everton": 561,
    "Garner_Everton": 570,
    "Onana_Everton": 577,
    "Welch_Everton": 605,
    "Gueye_Everton": 611,
    "Jakupovi\u0107_Everton": 627,
    "John_Everton": 637,
    "Cannon_Everton": 662,
    "Price_Everton": 678,
    "Simms_Everton": 686,
    "Samuels-Smith_Everton": 757,
    "Lonergan_Everton": 760,
    "C\u00e9dric_Fulham": 1,
    "Leno_Fulham": 2,
    "Duffy_Fulham": 105,
    "Cairney_Fulham": 200,
    "Ream_Fulham": 201,
    "Knockaert_Fulham": 202,
    "Chalobah_Fulham": 203,
    "Kebano_Fulham": 204,
    "De Cordova-Reid_Fulham": 205,
    "Bryan_Fulham": 206,
    "Gazzaniga_Fulham": 207,
    "Kongolo_Fulham": 208,
    "Tosin_Fulham": 209,
    "Mitrovi\u0107_Fulham": 210,
    "Reed_Fulham": 211,
    "Wilson_Fulham": 212,
    "Rod\u00e1k_Fulham": 213,
    "Cavaleiro_Fulham": 214,
    "Tete_Fulham": 215,
    "Onomah_Fulham": 216,
    "Robinson_Fulham": 217,
    "Muniz_Fulham": 218,
    "Stansfield_Fulham": 219,
    "Palhinha_Fulham": 220,
    "James_Fulham": 231,
    "Andreas_Fulham": 346,
    "Diop_Fulham": 470,
    "Francois_Fulham": 521,
    "Mbabu_Fulham": 532,
    "Harris_Fulham": 546,
    "Solomon_Fulham": 562,
    "Ablade_Fulham": 591,
    "Kurzawa_Fulham": 613,
    "Willian_Fulham": 614,
    "Vin\u00edcius_Fulham": 618,
    "Parkes_Fulham": 636,
    "Godo_Fulham": 641,
    "Sekularac_Fulham": 667,
    "Lukic_Fulham": 726,
    "Wickens_Fulham": 747,
    "C.Robinson_Fulham": 750,
    "Dibley-Dias_Fulham": 763,
    "Schmeichel_Leicester": 248,
    "Evans_Leicester": 249,
    "Bertrand_Leicester": 250,
    "Albrighton_Leicester": 251,
    "Mendy_Leicester": 252,
    "Vestergaard_Leicester": 253,
    "Ward_Leicester": 254,
    "Vardy_Leicester": 255,
    "Ricardo_Leicester": 256,
    "Amartey_Leicester": 257,
    "Castagne_Leicester": 258,
    "Tielemans_Leicester": 259,
    "P\u00e9rez_Leicester": 260,
    "Maddison_Leicester": 261,
    "Iheanacho_Leicester": 262,
    "Choudhury_Leicester": 263,
    "Barnes_Leicester": 264,
    "Ndidi_Leicester": 265,
    "Dewsbury-Hall_Leicester": 266,
    "S\u00f6y\u00fcnc\u00fc_Leicester": 267,
    "Justin_Leicester": 268,
    "Soumar\u00e9_Leicester": 269,
    "Thomas_Leicester": 270,
    "Daka_Leicester": 271,
    "Brunt_Leicester": 273,
    "Iversen_Leicester": 548,
    "Praet_Leicester": 549,
    "Smithies_Leicester": 581,
    "Faes_Leicester": 612,
    "Braybrooke_Leicester": 639,
    "Wormleighton_Leicester": 645,
    "McAteer_Leicester": 687,
    "Kristiansen_Leicester": 709,
    "Tet\u00ea_Leicester": 715,
    "Souttar_Leicester": 727,
    "Mar\u00e7al-Madivadua_Leicester": 735,
    "Cooper_Leeds": 221,
    "Ayling_Leeds": 222,
    "Klich_Leeds": 223,
    "Forshaw_Leeds": 224,
    "Rodrigo_Leeds": 225,
    "Dallas_Leeds": 226,
    "Bamford_Leeds": 227,
    "Llorente_Leeds": 228,
    "Roberts_Leeds": 229,
    "Koch_Leeds": 230,
    "Raphinha_Leeds": 232,
    "Harrison_Leeds": 233,
    "Shackleton_Leeds": 234,
    "Struijk_Leeds": 235,
    "Klaesson_Leeds": 236,
    "Greenwood_Leeds": 237,
    "Meslier_Leeds": 238,
    "Firpo_Leeds": 239,
    "Summerville_Leeds": 240,
    "Bate_Leeds": 241,
    "Gelhardt_Leeds": 242,
    "Hjelde_Leeds": 243,
    "Kristensen_Leeds": 244,
    "Roca_Leeds": 245,
    "Aaronson_Leeds": 246,
    "Gyabi_Leeds": 247,
    "Adams_Leeds": 506,
    "Sinisterra_Leeds": 508,
    "Drameh_Leeds": 547,
    "Gray_Leeds": 565,
    "Robles_Leeds": 578,
    "Gnonto_Leeds": 619,
    "Mateo Joseph_Leeds": 659,
    "Perkins_Leeds": 663,
    "W\u00f6ber_Leeds": 691,
    "Rutter_Leeds": 700,
    "McKennie_Leeds": 720,
    "Chilokoa-Mullen_Leeds": 742,
    "Monteiro_Leeds": 743,
    "Milner_Liverpool": 274,
    "Henderson_Liverpool": 275,
    "Matip_Liverpool": 276,
    "Thiago_Liverpool": 277,
    "Chamberlain_Liverpool": 278,
    "Firmino_Liverpool": 279,
    "Van Dijk_Liverpool": 280,
    "Alisson_Liverpool": 281,
    "Fabinho_Liverpool": 282,
    "Salah_Liverpool": 283,
    "Robertson_Liverpool": 284,
    "Alexander-Arnold_Liverpool": 285,
    "Gomez_Liverpool": 286,
    "Keita_Liverpool": 287,
    "Diogo Jota_Liverpool": 288,
    "Kelleher_Liverpool": 289,
    "Konat\u00e9_Liverpool": 290,
    "Jones_Liverpool": 291,
    "Tsimikas_Liverpool": 292,
    "Luis D\u00edaz_Liverpool": 293,
    "Elliott_Liverpool": 294,
    "Carvalho_Liverpool": 296,
    "Darwin_Liverpool": 297,
    "Ramsay_Liverpool": 298,
    "Adri\u00e1n_Liverpool": 497,
    "R.Williams_Liverpool": 498,
    "Davies_Liverpool": 499,
    "Van den Berg_Liverpool": 500,
    "Phillips_Liverpool": 501,
    "Chambers_Liverpool": 563,
    "Bajcetic_Liverpool": 564,
    "Clark_Liverpool": 584,
    "H.Davies_Liverpool": 592,
    "Arthur_Liverpool": 620,
    "Doak_Liverpool": 665,
    "Gakpo_Liverpool": 680,
    "Walker_Man City": 299,
    "G\u00fcndogan_Man City": 300,
    "De Bruyne_Man City": 301,
    "Stones_Man City": 302,
    "Mahrez_Man City": 303,
    "Grealish_Man City": 305,
    "Cancelo_Man City": 306,
    "Ederson_Man City": 307,
    "Ak\u00e9_Man City": 308,
    "Laporte_Man City": 309,
    "Steffen_Man City": 310,
    "Bernardo_Man City": 311,
    "Dias_Man City": 312,
    "Foden_Man City": 314,
    "Rodri_Man City": 315,
    "Palmer_Man City": 316,
    "McAtee_Man City": 317,
    "Haaland_Man City": 318,
    "\u00c1lvarez_Man City": 319,
    "Mbete_Man City": 320,
    "Wilson-Esbrand_Man City": 322,
    "Delap_Man City": 323,
    "Ortega_Man City": 324,
    "Phillips_Man City": 325,
    "Carson_Man City": 502,
    "Lewis_Man City": 573,
    "Sergio G\u00f3mez_Man City": 587,
    "Gomes_Man City": 599,
    "Knight_Man City": 600,
    "Akanji_Man City": 610,
    "Perrone_Man City": 712,
    "Butland_Man Utd": 162,
    "Ronaldo_Man Utd": 326,
    "De Gea_Man Utd": 327,
    "Jones_Man Utd": 328,
    "Varane_Man Utd": 329,
    "Maguire_Man Utd": 330,
    "Fred_Man Utd": 331,
    "Shaw_Man Utd": 332,
    "Fernandes_Man Utd": 333,
    "Telles_Man Utd": 334,
    "Rashford_Man Utd": 335,
    "Van de Beek_Man Utd": 336,
    "Lindel\u00f6f_Man Utd": 337,
    "McTominay_Man Utd": 338,
    "Bailly_Man Utd": 339,
    "Sancho_Man Utd": 340,
    "Wan-Bissaka_Man Utd": 341,
    "Dalot_Man Utd": 342,
    "B.Williams_Man Utd": 343,
    "Elanga_Man Utd": 344,
    "Martial_Man Utd": 345,
    "Pellistri_Man Utd": 347,
    "Heaton_Man Utd": 348,
    "Malacia_Man Utd": 504,
    "Eriksen_Man Utd": 519,
    "Mart\u00ednez_Man Utd": 533,
    "Amad_Man Utd": 550,
    "Iqbal_Man Utd": 551,
    "Garnacho_Man Utd": 569,
    "Casemiro_Man Utd": 593,
    "Antony_Man Utd": 609,
    "Kov\u00e1r_Man Utd": 615,
    "Mainoo_Man Utd": 643,
    "Bishop_Man Utd": 656,
    "Shoretire_Man Utd": 660,
    "Bennett_Man Utd": 674,
    "Weghorst_Man Utd": 701,
    "Sabitzer_Man Utd": 728,
    "Jurado_Man Utd": 759,
    "Gordon_Newcastle": 195,
    "Ritchie_Newcastle": 350,
    "Fern\u00e1ndez_Newcastle": 351,
    "Clark_Newcastle": 352,
    "Darlow_Newcastle": 353,
    "Dubravka_Newcastle": 355,
    "Wilson_Newcastle": 356,
    "Trippier_Newcastle": 357,
    "Burn_Newcastle": 358,
    "Fraser_Newcastle": 359,
    "Lascelles_Newcastle": 360,
    "Gayle_Newcastle": 361,
    "Dummett_Newcastle": 362,
    "Manquillo_Newcastle": 363,
    "Krafth_Newcastle": 364,
    "Murphy_Newcastle": 365,
    "Sch\u00e4r_Newcastle": 366,
    "Targett_Newcastle": 367,
    "Saint-Maximin_Newcastle": 368,
    "Almir\u00f3n_Newcastle": 369,
    "S.Longstaff_Newcastle": 370,
    "Joelinton_Newcastle": 371,
    "Lewis_Newcastle": 372,
    "Willock_Newcastle": 373,
    "Bruno Guimar\u00e3es_Newcastle": 374,
    "Hendrick_Newcastle": 375,
    "Pope_Newcastle": 376,
    "Botman_Newcastle": 377,
    "Anderson_Newcastle": 552,
    "Ashby_Newcastle": 555,
    "Isak_Newcastle": 594,
    "Karius_Newcastle": 626,
    "Kuol_Newcastle": 683,
    "Miley_Newcastle": 741,
    "N.Williams_Nott'm Forest": 295,
    "Shelvey_Nott'm Forest": 349,
    "Wood_Nott'm Forest": 354,
    "Arter_Nott'm Forest": 378,
    "Cook_Nott'm Forest": 379,
    "Lyle Taylor_Nott'm Forest": 380,
    "Colback_Nott'm Forest": 381,
    "Samba_Nott'm Forest": 382,
    "Caf\u00fa_Nott'm Forest": 383,
    "Lolley_Nott'm Forest": 384,
    "McKenna_Nott'm Forest": 385,
    "Dr\u00e4ger_Nott'm Forest": 386,
    "Yates_Nott'm Forest": 387,
    "Worrall_Nott'm Forest": 388,
    "Panzo_Nott'm Forest": 389,
    "Xande Silva_Nott'm Forest": 390,
    "Surridge_Nott'm Forest": 391,
    "Laryea_Nott'm Forest": 392,
    "Mbe Soh_Nott'm Forest": 393,
    "Johnson_Nott'm Forest": 394,
    "Mighten_Nott'm Forest": 395,
    "Ojeda_Nott'm Forest": 396,
    "Awoniyi_Nott'm Forest": 397,
    "Henderson_Nott'm Forest": 398,
    "Biancone_Nott'm Forest": 399,
    "Boly_Nott'm Forest": 474,
    "Gibbs-White_Nott'm Forest": 493,
    "Niakhat\u00e9_Nott'm Forest": 507,
    "Richards_Nott'm Forest": 511,
    "Hennessey_Nott'm Forest": 518,
    "Toffolo_Nott'm Forest": 523,
    "O'Brien_Nott'm Forest": 524,
    "Lingard_Nott'm Forest": 527,
    "Mangala_Nott'm Forest": 536,
    "Hammond_Nott'm Forest": 553,
    "Freuler_Nott'm Forest": 582,
    "Kouyat\u00e9_Nott'm Forest": 583,
    "Dennis_Nott'm Forest": 585,
    "Renan Lodi_Nott'm Forest": 602,
    "Bad\u00e9_Nott'm Forest": 621,
    "Aurier_Nott'm Forest": 628,
    "Dale Taylor_Nott'm Forest": 666,
    "Smith_Nott'm Forest": 675,
    "Scarpa_Nott'm Forest": 681,
    "Danilo_Nott'm Forest": 703,
    "Navas_Nott'm Forest": 729,
    "Felipe_Nott'm Forest": 730,
    "A.Ayew_Nott'm Forest": 734,
    "G.Shelvey_Nott'm Forest": 749,
    "Maitland-Niles_Southampton": 21,
    "Lavia_Southampton": 321,
    "Walcott_Southampton": 400,
    "McCarthy_Southampton": 401,
    "Romeu_Southampton": 402,
    "Redmond_Southampton": 403,
    "S.Armstrong_Southampton": 405,
    "Elyounoussi_Southampton": 406,
    "Ward-Prowse_Southampton": 407,
    "A.Armstrong_Southampton": 408,
    "Walker-Peters_Southampton": 409,
    "Bednarek_Southampton": 410,
    "Adams_Southampton": 411,
    "Tella_Southampton": 412,
    "Lyanco_Southampton": 413,
    "Valery_Southampton": 414,
    "Smallbone_Southampton": 415,
    "Diallo_Southampton": 416,
    "Perraud_Southampton": 417,
    "Djenepo_Southampton": 418,
    "Livramento_Southampton": 419,
    "Salisu_Southampton": 420,
    "Lis_Southampton": 421,
    "Bazunu_Southampton": 422,
    "Bella-Kotchap_Southampton": 423,
    "Caballero_Southampton": 424,
    "Aribo_Southampton": 512,
    "Mara_Southampton": 528,
    "Larios_Southampton": 622,
    "Caleta-Car_Southampton": 623,
    "Edozie_Southampton": 624,
    "Payne_Southampton": 647,
    "Finnigan_Southampton": 648,
    "Morgan_Southampton": 671,
    "Orsic_Southampton": 692,
    "Alcaraz_Southampton": 693,
    "Bree_Southampton": 716,
    "Kamaldeen_Southampton": 731,
    "Onuachu_Southampton": 732,
    "Lloris_Spurs": 425,
    "Forster_Spurs": 426,
    "Kane_Spurs": 427,
    "Son_Spurs": 428,
    "Doherty_Spurs": 429,
    "Dier_Spurs": 430,
    "Lucas Moura_Spurs": 431,
    "Davies_Spurs": 432,
    "H\u00f8jbjerg_Spurs": 433,
    "Winks_Spurs": 434,
    "S\u00e1nchez_Spurs": 435,
    "R.Sessegnon_Spurs": 436,
    "Bergwijn_Spurs": 437,
    "Reguil\u00f3n_Spurs": 438,
    "Tanganga_Spurs": 439,
    "Bentancur_Spurs": 440,
    "Skipp_Spurs": 441,
    "Rodon_Spurs": 442,
    "Romero_Spurs": 443,
    "Bissouma_Spurs": 444,
    "Emerson Royal_Spurs": 445,
    "Kulusevski_Spurs": 446,
    "Scarlett_Spurs": 447,
    "Peri\u0161i\u0107_Spurs": 448,
    "White_Spurs": 449,
    "Sarr_Spurs": 450,
    "Austin_Spurs": 451,
    "Devine_Spurs": 452,
    "Parrott_Spurs": 453,
    "Richarlison_Spurs": 454,
    "Lenglet_Spurs": 513,
    "Spence_Spurs": 522,
    "Bryan_Spurs": 554,
    "Danjuma_Spurs": 713,
    "Pedro Porro_Spurs": 733,
    "Mundle_Spurs": 748,
    "Abbott_Spurs": 758,
    "Ings_West Ham": 30,
    "Fabianski_West Ham": 455,
    "Ogbonna_West Ham": 456,
    "Cresswell_West Ham": 457,
    "Antonio_West Ham": 458,
    "Lanzini_West Ham": 460,
    "Zouma_West Ham": 461,
    "Masuaku_West Ham": 462,
    "Coufal_West Ham": 463,
    "Benrahma_West Ham": 464,
    "Bowen_West Ham": 465,
    "Vlasic_West Ham": 466,
    "Rice_West Ham": 467,
    "Soucek_West Ham": 468,
    "Fornals_West Ham": 469,
    "Johnson_West Ham": 471,
    "Aguerd_West Ham": 472,
    "Areola_West Ham": 473,
    "Downes_West Ham": 509,
    "Scamacca_West Ham": 529,
    "Emerson_West Ham": 545,
    "Coventry_West Ham": 556,
    "Oko-Flex_West Ham": 572,
    "Cornet_West Ham": 575,
    "Kehrer_West Ham": 588,
    "Paquet\u00e1_West Ham": 603,
    "Mubama_West Ham": 669,
    "Anang_West Ham": 739,
    "Hegyi_West Ham": 740,
    "Casey_West Ham": 746,
    "Dawson_Wolves": 459,
    "Jim\u00e9nez_Wolves": 476,
    "Jonny_Wolves": 477,
    "S\u00e1_Wolves": 478,
    "Neves_Wolves": 480,
    "Hwang_Wolves": 481,
    "Semedo_Wolves": 482,
    "Podence_Wolves": 483,
    "Kilman_Wolves": 484,
    "Cundle_Wolves": 485,
    "Neto_Wolves": 486,
    "A\u00eft-Nouri_Wolves": 487,
    "Fabio Silva_Wolves": 488,
    "Toti_Wolves": 489,
    "Chiquinho_Wolves": 490,
    "Adama_Wolves": 491,
    "\u0160arki\u0107_Wolves": 492,
    "Mosquera_Wolves": 494,
    "Moutinho_Wolves": 503,
    "Collins_Wolves": 516,
    "Smith_Wolves": 557,
    "Bueno_Wolves": 558,
    "Hodge_Wolves": 566,
    "Ronan_Wolves": 567,
    "Campbell_Wolves": 568,
    "Guedes_Wolves": 579,
    "Matheus_Wolves": 589,
    "Kalajd\u017ei\u0107_Wolves": 608,
    "Diego Costa_Wolves": 625,
    "Traor\u00e9_Wolves": 629,
    "Fraser_Wolves": 657,
    "Griffiths_Wolves": 658,
    "Lembikisa_Wolves": 664,
    "Cunha_Wolves": 682,
    "Lemina_Wolves": 698,
    "Sarabia_Wolves": 704,
    "Bentley_Wolves": 717,
    "Jo\u00e3o Gomes_Wolves": 721
}